odoo/addons/portal_sale_personal_data_only/README.rst
odoo/addons/portal_sale_personal_data_only/__init__.py
odoo/addons/portal_sale_personal_data_only/__manifest__.py
odoo/addons/portal_sale_personal_data_only/hooks.py
odoo/addons/portal_sale_personal_data_only/data/portal_sale_security.xml
odoo/addons/portal_sale_personal_data_only/i18n/ca.po
odoo/addons/portal_sale_personal_data_only/i18n/de.po
odoo/addons/portal_sale_personal_data_only/i18n/es.po
odoo/addons/portal_sale_personal_data_only/i18n/portal_sale_personal_data_only.pot
odoo/addons/portal_sale_personal_data_only/i18n/zh_CN.po
odoo/addons/portal_sale_personal_data_only/readme/CONTRIBUTORS.rst
odoo/addons/portal_sale_personal_data_only/readme/DESCRIPTION.rst
odoo/addons/portal_sale_personal_data_only/readme/USAGE.rst
odoo/addons/portal_sale_personal_data_only/static/description/icon.png
odoo/addons/portal_sale_personal_data_only/static/description/index.html
odoo12_addon_portal_sale_personal_data_only-12.0.1.1.1.dist-info/METADATA
odoo12_addon_portal_sale_personal_data_only-12.0.1.1.1.dist-info/WHEEL
odoo12_addon_portal_sale_personal_data_only-12.0.1.1.1.dist-info/top_level.txt
odoo12_addon_portal_sale_personal_data_only-12.0.1.1.1.dist-info/RECORD
